dann5/__init__.py
dann5/azure.py
dann5/azureWS.py
dann5/d5.cp310-win_amd64.pyd
dann5/d5.cpython-310-darwin.so
dann5/d5.so
dann5/d5o.cp310-win_amd64.pyd
dann5/d5o.cpython-310-darwin.so
dann5/d5o.so
dann5/d5q.cp310-win_amd64.pyd
dann5/d5q.cpython-310-darwin.so
dann5/d5q.so
dann5/dwave.py
dann5/qiskit.py
dann5-3.0.1.dist-info/LICENSE
dann5-3.0.1.dist-info/METADATA
dann5-3.0.1.dist-info/WHEEL
dann5-3.0.1.dist-info/top_level.txt
dann5-3.0.1.dist-info/RECORD
