Metadata-Version: 2.1
Name: dann5
Version: 3.0.1
Summary: A quantum programming integrated platform for fast learning of quantum computing concepts and development of quantum programs
Home-page: https://github.com/voya-voja/dann5.3
Author: voya-voja
Author-email: nebojsa@nand5.onmicrosoft.com
License: GPLv3
Project-URL: Bug Tracker, https://github.com/voya-voja/dann5.3/issues
Keywords: quantum computing programming coding language development types dwave ibm azure
Classifier: Development Status :: 3 - Alpha
Classifier: Development Status :: 4 - Beta
Classifier: Environment :: OpenStack
Classifier: Environment :: Plugins
Classifier: Environment :: Other Environment
Classifier: Framework :: IPython
Classifier: Framework :: Jupyter :: JupyterLab
Classifier: Framework :: Jupyter :: JupyterLab :: Extensions
Classifier: Intended Audience :: Developers
Classifier: Intended Audience :: Education
Classifier: Intended Audience :: Information Technology
Classifier: Intended Audience :: Science/Research
Classifier: Intended Audience :: Science/Research
Classifier: Intended Audience :: Financial and Insurance Industry
Classifier: Intended Audience :: Healthcare Industry
Classifier: Intended Audience :: Telecommunications Industry
Classifier: Intended Audience :: Other Audience
Classifier: License :: OSI Approved :: GNU General Public License v3 (GPLv3)
Classifier: Natural Language :: English
Classifier: Operating System :: Microsoft :: Windows :: Windows 10
Classifier: Operating System :: Microsoft :: Windows :: Windows 11
Classifier: Operating System :: MacOS :: MacOS X
Classifier: Operating System :: POSIX :: Linux
Classifier: Programming Language :: C++
Classifier: Programming Language :: Python :: 3.10
Classifier: Topic :: Security
Classifier: Topic :: Software Development
Classifier: Topic :: Scientific/Engineering :: Interface Engine/Protocol Translator
Classifier: Topic :: Scientific/Engineering :: Artificial Intelligence
Classifier: Topic :: Scientific/Engineering :: Information Analysis
Classifier: Topic :: Scientific/Engineering :: Mathematics
Classifier: Topic :: Scientific/Engineering :: Physics
Classifier: Topic :: Software Development :: Libraries :: Application Frameworks
Classifier: Topic :: Software Development :: Libraries :: Python Modules
Classifier: Topic :: Software Development :: Build Tools
Classifier: Topic :: Software Development :: Code Generators
Classifier: Topic :: Software Development :: Compilers
Classifier: Topic :: Software Development :: Debuggers
Classifier: Topic :: Software Development :: Interpreters
Classifier: Topic :: Software Development :: Embedded Systems
Classifier: Topic :: System :: Distributed Computing
Requires-Python: >=3.10
License-File: LICENSE
Requires-Dist: pybind11
